[{"title":"Ensiferum - March of war / Axe of judgement [Inner Oni]","mods":"0","beatmapId":2370260,"ppOld":483,"ppNew":479},{"title":"DragonForce - Through the Fire and Flames [Tatsujin]","mods":"0","beatmapId":2333147,"ppOld":415,"ppNew":467},{"title":"Yousei Teikoku - Fata Morgana [Sorrow]","mods":"0","beatmapId":4675546,"ppOld":476,"ppNew":465},{"title":"Noah - Deadly force - Put an end [Finale]","mods":"256","beatmapId":2325977,"ppOld":420,"ppNew":459},{"title":"Ne Obliviscaris - Devour Me, Colossus (Part I): Blackholes [Of Hope And White Fire]","mods":"0","beatmapId":2333970,"ppOld":409,"ppNew":456},{"title":"Demetori - Fuujin Shoujo [Ura Oni]","mods":"0","beatmapId":1486175,"ppOld":443,"ppNew":452},{"title":"Ito Kanako - Sky of Twilight [Oni]","mods":"0","beatmapId":1398803,"ppOld":407,"ppNew":451},{"title":"BABYMETAL - Road of Resistance [Tatsujin]","mods":"0","beatmapId":935271,"ppOld":470,"ppNew":447},{"title":"Dragon Guardian - Tsuioku no Kuroki Makenshi [Knight Oni]","mods":"0","beatmapId":1874646,"ppOld":449,"ppNew":447},{"title":"Primary - Inai Sekai [Yuramoxx' Inner Oni]","mods":"0","beatmapId":1191922,"ppOld":457,"ppNew":442},{"title":"ARForest - Prometheus [The Fire of Prometheus]","mods":"0","beatmapId":2580106,"ppOld":399,"ppNew":442},{"title":"Pascal Michael Stiefel - Collapsing Rift [Hurry Up!]","mods":"0","beatmapId":2499632,"ppOld":393,"ppNew":442},{"title":"VINXIS - Sidetracked Day [Sidetracked Oni]","mods":"0","beatmapId":1603503,"ppOld":437,"ppNew":434},{"title":"Demetori - Kamisabita Kosenjou ~ Suwa Foughten Field [Inner Oni]","mods":"0","beatmapId":1530713,"ppOld":382,"ppNew":430},{"title":"xi - Ascension to Heaven [Ascent]","mods":"0","beatmapId":1453460,"ppOld":390,"ppNew":428},{"title":"DragonForce - Extraction Zone [Tatsujin]","mods":"0","beatmapId":1402693,"ppOld":427,"ppNew":426},{"title":"DECO*27 - Ghost Rule [Mayday]","mods":"0","beatmapId":1315674,"ppOld":463,"ppNew":424},{"title":"chelmico - Easy Breezy feat. Zenpaku (dj-Jo Remix) [Breeze]","mods":"0","beatmapId":2346527,"ppOld":382,"ppNew":424},{"title":"Onocchi, Xenon - Suigetsu Kyouka Koubou Issen [Oni]","mods":"0","beatmapId":672474,"ppOld":429,"ppNew":419},{"title":"ROKINA - Icicle Stinger [TAIKO-HOLIC]","mods":"256","beatmapId":764946,"ppOld":420,"ppNew":419},{"title":"DJ Sharpnel - Back to the gate [Inner Oni]","mods":"0","beatmapId":2427975,"ppOld":418,"ppNew":417},{"title":"GYZE - HONESTY [Rebellion]","mods":"0","beatmapId":1574205,"ppOld":394,"ppNew":417},{"title":"AKIAKANE - Hanabira (Irus Brutalcore Breaks Remix) [Inner Oni]","mods":"0","beatmapId":1661121,"ppOld":386,"ppNew":417},{"title":"Moetan Cast - Mahou Shoujo Magical-tan! (ETIA. Hardcore Remix) [Magical Oni]","mods":"0","beatmapId":1888929,"ppOld":393,"ppNew":416},{"title":"Xandria - Call Of Destiny [Inner Oni]","mods":"0","beatmapId":1348707,"ppOld":388,"ppNew":415},{"title":"DragonForce - Storming the Burning Fields [Tatsujin]","mods":"0","beatmapId":2058126,"ppOld":413,"ppNew":413},{"title":"yaseta - Bluenation [Approaching Horizon]","mods":"0","beatmapId":2400474,"ppOld":379,"ppNew":413},{"title":"ROKINA - MachinaRegina [Regal Oni]","mods":"0","beatmapId":2401576,"ppOld":367,"ppNew":413},{"title":"Reol - Streaming Heart [Inner Oni]","mods":"0","beatmapId":890435,"ppOld":452,"ppNew":411},{"title":"Camellia - Feelin Sky (Camellia's \"200step\" Self-remix) [Falling to the Ground]","mods":"0","beatmapId":1580327,"ppOld":375,"ppNew":411},{"title":"Camellia - Fastest Crash [Crash]","mods":"0","beatmapId":1000101,"ppOld":420,"ppNew":410},{"title":"LiSA - oath sign (brz_bootleg_remix) [Servant Oni]","mods":"0","beatmapId":2276637,"ppOld":397,"ppNew":410},{"title":"B-ko (CV: Touyama Nao) - Nisemono Chuuihou [Doppelganger]","mods":"256","beatmapId":2421236,"ppOld":413,"ppNew":409},{"title":"Blind Guardian - A Voice in the Dark [Hell Oni]","mods":"0","beatmapId":1301568,"ppOld":386,"ppNew":409},{"title":"DragonForce - Defenders [Tatsujin]","mods":"0","beatmapId":835691,"ppOld":413,"ppNew":408},{"title":"Unlucky Morpheus - Black Pentagram [Inner Oni]","mods":"0","beatmapId":2336446,"ppOld":408,"ppNew":406},{"title":"FELT - Lies in Reality [Dissembler]","mods":"0","beatmapId":1407618,"ppOld":365,"ppNew":406},{"title":"HARI KARI - MIRROR FRAGMENT [INNER ONI]","mods":"0","beatmapId":2034220,"ppOld":407,"ppNew":405},{"title":"DJ SHARPNEL - Pacific Girls [Divine Orchestra]","mods":"0","beatmapId":4597047,"ppOld":424,"ppNew":404},{"title":"ClariS - Colorful (tamame's apostate remix) [Evil]","mods":"0","beatmapId":1879405,"ppOld":415,"ppNew":404},{"title":"DystopiaGround - AugoEidEs [Inner Oni]","mods":"0","beatmapId":1082284,"ppOld":415,"ppNew":404},{"title":"ke-ji feat. Nanahira - Ange du Blanc Pur [Lueur Divine]","mods":"0","beatmapId":2627023,"ppOld":409,"ppNew":404},{"title":"BABYMETAL - Tales of The Destinies [Chromoxx' Nightmare Oni]","mods":"0","beatmapId":1207233,"ppOld":403,"ppNew":404},{"title":"Fire EX. - Shattered Dreams [Ishida's Inner Oni]","mods":"0","beatmapId":719587,"ppOld":381,"ppNew":403},{"title":"LiSA - Rising Hope (LU-I Remix) [Irregularity]","mods":"0","beatmapId":1621929,"ppOld":386,"ppNew":402},{"title":"Hayakore Tatsumi - Wedding of the Goodbye [Louise the Zero]","mods":"0","beatmapId":2708053,"ppOld":407,"ppNew":401},{"title":"UNDEAD CORPORATION - The Empress [Hell Oni]","mods":"256","beatmapId":2420013,"ppOld":384,"ppNew":401},{"title":"Renard - Usual Shitking [Inner Oni]","mods":"0","beatmapId":1868785,"ppOld":377,"ppNew":401},{"title":"Nanahira - Petals [Fragments]","mods":"0","beatmapId":1418603,"ppOld":403,"ppNew":399},{"title":"Shounen Radio - neu [Collab]","mods":"0","beatmapId":371219,"ppOld":391,"ppNew":398},{"title":"Wagakki Band - Tengaku [Heavenly Oni]","mods":"0","beatmapId":1025779,"ppOld":401,"ppNew":397},{"title":"Morimori Atsushi - PUPA [Inner Oni]","mods":"0","beatmapId":545843,"ppOld":400,"ppNew":397},{"title":"Yousei Teikoku - Hades:The end [Inner Oni]","mods":"0","beatmapId":683188,"ppOld":402,"ppNew":396},{"title":"Krewella - Come And Get It (Razihel Remix) [Inner Oni]","mods":"0","beatmapId":903809,"ppOld":415,"ppNew":394},{"title":"Demetori - Kagayaku Hari no Kobito-zoku ~ Counter-Attack of the Weak [Tatsujin]","mods":"0","beatmapId":887675,"ppOld":395,"ppNew":393},{"title":"Camellia feat. Nanahira - Force! [Magical Force!]","mods":"0","beatmapId":1877830,"ppOld":378,"ppNew":393},{"title":"BlackY - RAINBOW TO THE GALAXIES [RAINBOW]","mods":"0","beatmapId":1408023,"ppOld":393,"ppNew":392},{"title":"LiLA'c Records - Aimless Voyage [Ayyri's Inner Oni]","mods":"0","beatmapId":1509444,"ppOld":393,"ppNew":392},{"title":"DECO*27 - Chimera feat. Hatsune Miku [Chromoxx' Hell Oni]","mods":"0","beatmapId":3557958,"ppOld":401,"ppNew":391},{"title":"onoken - K8107 [Inner Oni]","mods":"0","beatmapId":2502210,"ppOld":392,"ppNew":391},{"title":"Kobaryo - New Game Plus [Inner Oni]","mods":"0","beatmapId":2598377,"ppOld":393,"ppNew":390},{"title":"DECO*27 - HIBANA feat. Hatsune Miku [Headshot]","mods":"0","beatmapId":1828695,"ppOld":416,"ppNew":389},{"title":"Getty vs. DJ DiA - Ops:Code-Rapture- [Outer Oni]","mods":"0","beatmapId":1593442,"ppOld":374,"ppNew":388},{"title":"Thaehan - Doki-Doki [Ayyri's Outer Oni]","mods":"0","beatmapId":1319597,"ppOld":366,"ppNew":388},{"title":"Omoi - Chiisana Koi no Uta (Synth Rock Cover) [Ono's Oni]","mods":"0","beatmapId":1360616,"ppOld":404,"ppNew":387},{"title":"Various Artists - International OTOMAD's 6 [Inner Oni]","mods":"0","beatmapId":916603,"ppOld":375,"ppNew":387},{"title":"USAO - USAO ULTIMATE HYPER MEGA MIX [TKS x ARRIVAL'S ULTIMATE HYPER MEGA ONI]","mods":"0","beatmapId":1970039,"ppOld":388,"ppNew":385},{"title":"Loctek - Oldskool [Inner Oni]","mods":"0","beatmapId":1786235,"ppOld":364,"ppNew":384},{"title":"Nanaki feat.GUMI - Mousou Kajitsu [Delusional Fantasy]","mods":"0","beatmapId":1273614,"ppOld":392,"ppNew":383},{"title":"LeaF - Wizdomiot [JuDa's Inner Oni]","mods":"0","beatmapId":781859,"ppOld":386,"ppNew":383},{"title":"Dancing Dolls - monochrome (Asterisk Makina Remix) [Destiny]","mods":"0","beatmapId":2012389,"ppOld":385,"ppNew":383},{"title":"Resonecia - Legende [Legendary Oni]","mods":"0","beatmapId":380524,"ppOld":374,"ppNew":383},{"title":"fhana - Wonder Stella [Chromoyams' Inner Oni]","mods":"0","beatmapId":1414482,"ppOld":389,"ppNew":381},{"title":"L.E.D. vs S-C-U - Confiserie [Inner Oni]","mods":"0","beatmapId":809880,"ppOld":385,"ppNew":381},{"title":"Dougal & Gammer - Brainstorm [Make Up Your Mind]","mods":"0","beatmapId":3511546,"ppOld":369,"ppNew":381},{"title":"Laur - Sound Chimera [Cosmic Minds]","mods":"0","beatmapId":1637636,"ppOld":383,"ppNew":380},{"title":"WAiKURO - Androgynos (Full Phase) [Ultimate]","mods":"0","beatmapId":1410506,"ppOld":369,"ppNew":380},{"title":"fhana - Comet Lucifer ~The Seed and the Sower~ [Inner Oni]","mods":"0","beatmapId":1860941,"ppOld":382,"ppNew":378},{"title":"Itou Kanako - Uncontrollable [Uncontrollable Oni]","mods":"0","beatmapId":1358048,"ppOld":382,"ppNew":377},{"title":"Jeff Williams feat. Casey Lee Williams, Sandy Casey - Red Like Roses part I & II [The Story of Little Red Riding Hood]","mods":"0","beatmapId":2283932,"ppOld":371,"ppNew":377},{"title":"Fractal Dreamers - Gardens Under A Spring Sky [Fapu's Verdancy]","mods":"0","beatmapId":2266329,"ppOld":367,"ppNew":377},{"title":"Kurokotei - Galaxy Collapse [Oni]","mods":"256","beatmapId":727903,"ppOld":383,"ppNew":376},{"title":"DJ Sharpnel - WE LUV LAMA [Oni]","mods":"256","beatmapId":1436969,"ppOld":377,"ppNew":374},{"title":"Virtual Self - EON BREAK [Inner Oni]","mods":"0","beatmapId":2377792,"ppOld":376,"ppNew":372},{"title":"xi - Last Resort [Genjuro's Inner Oni]","mods":"0","beatmapId":2365298,"ppOld":375,"ppNew":371},{"title":"t+pazolite - Because I was so Young [Innocence]","mods":"0","beatmapId":2269920,"ppOld":372,"ppNew":371},{"title":"Kaede To Kyo Aki Ame Kuzu - Q [Answer]","mods":"0","beatmapId":2343680,"ppOld":374,"ppNew":370},{"title":"S3RL feat Harri Rush - Nostalgic (Nightcore Mix) [Nardo's Taiko Inner Oni]","mods":"0","beatmapId":1282805,"ppOld":373,"ppNew":369},{"title":"mafumafu - Hello Dystopia [Collapsing Reality]","mods":"0","beatmapId":1697683,"ppOld":371,"ppNew":369},{"title":"rejection - Aimai Attitude (feat. Nakamura Sanso) [Aimai Oni]","mods":"0","beatmapId":3792679,"ppOld":370,"ppNew":368},{"title":"Chroma - Collapse [Inner Oni]","mods":"0","beatmapId":1463029,"ppOld":369,"ppNew":368},{"title":"Nekrogoblikon - The Skin Thief [Green's Oni]","mods":"0","beatmapId":2429855,"ppOld":370,"ppNew":367},{"title":"Mitsunori Ikeda feat. Aimee B - Fallen Angel (el poco maro Remix) [Icarus]","mods":"0","beatmapId":2287337,"ppOld":369,"ppNew":367},{"title":"tiku sens - fly a rocket to the center of your heart [lost in space]","mods":"0","beatmapId":2882110,"ppOld":368,"ppNew":366},{"title":"DragonForce - Chemical Interference [Tatsujin]","mods":"0","beatmapId":1240578,"ppOld":366,"ppNew":364},{"title":"A? - Arrogation (Cut Ver.) [Inner Oni]","mods":"0","beatmapId":2680771,"ppOld":366,"ppNew":363},{"title":"Zmey Gorynich - Sorochinskaya Yarmarka [Inner Oni]","mods":"0","beatmapId":3089091,"ppOld":370,"ppNew":360},{"title":"marina - Towa yori Towa ni [Inner Oni]","mods":"0","beatmapId":1170442,"ppOld":374,"ppNew":357},{"title":"toby fox - Spider Dance [Spider Donut 9999G]","mods":"0","beatmapId":818080,"ppOld":368,"ppNew":357},{"title":"xi - FREEDOM DiVE [Ono's Taiko Inner Oni]","mods":"0","beatmapId":161274,"ppOld":365,"ppNew":356}]