[{"title":"Toby Fox - alarm_titlescreen [Dog Alert!]","mods":"16","beatmapId":3301531,"ppOld":293,"ppNew":322},{"title":"Kobaryo - Kick To The Sky [Inner Oni]","mods":"0","beatmapId":3137646,"ppOld":313,"ppNew":310},{"title":"toby fox - Song That Might Play When You Fight Sans [Ura Oni]","mods":"0","beatmapId":4346312,"ppOld":308,"ppNew":306},{"title":"Lon - Yuru Fuwa Jukai Girl [Tasha's Taiko Oni]","mods":"0","beatmapId":165988,"ppOld":306,"ppNew":302},{"title":"Kuhaku Gokko - Zettai Zetsumei [Inner Oni]","mods":"0","beatmapId":4095198,"ppOld":298,"ppNew":297},{"title":"Kenshi Yonezu - KICK BACK (TV Size) [CHAINSAW DEVIL]","mods":"0","beatmapId":3848144,"ppOld":291,"ppNew":288},{"title":"DECO*27 - Chimera feat. Hatsune Miku [Dependency]","mods":"0","beatmapId":3622656,"ppOld":275,"ppNew":266},{"title":"LeaF - Calamity Fortune [Roxy's Inner Oni]","mods":"0","beatmapId":3741640,"ppOld":274,"ppNew":259},{"title":"TOMINAGA TOMMY HIROAKI - JoJo ~Sono Chi no Sadame~ Archetype MIX Ver. (Cut Ver.) [Overdrive]","mods":"0","beatmapId":3140729,"ppOld":249,"ppNew":246},{"title":"TUYU - Daemonisch [Bestrafung]","mods":"0","beatmapId":2971172,"ppOld":248,"ppNew":244},{"title":"sak respect for Arata Iiyoshi - Reason of being [Ura Oni]","mods":"0","beatmapId":1699509,"ppOld":228,"ppNew":239},{"title":"DECO*27 - Animal feat. Hatsune Miku [Chromoxx' Inner Oni]","mods":"0","beatmapId":3621632,"ppOld":243,"ppNew":238},{"title":"Will Stetson - First Storm -Japanese Version- [Cychlo's Inner Oni]","mods":"0","beatmapId":2520065,"ppOld":238,"ppNew":236},{"title":"TUYU - Under Kids [arc & ler's Counterattack]","mods":"0","beatmapId":3726149,"ppOld":236,"ppNew":235},{"title":"t+pazolite - Night of Knights (tpz Overheat Remix) [Inner Oni]","mods":"0","beatmapId":2156726,"ppOld":212,"ppNew":229},{"title":"Ado - Ashura-chan [Inner Oni]","mods":"0","beatmapId":3441318,"ppOld":226,"ppNew":228},{"title":"CHiCO with HoneyWorks - Kessen Spirit (TV Size) [iRedi's Resolve]","mods":"0","beatmapId":4214168,"ppOld":219,"ppNew":228},{"title":"Nor feat. Konomi Kohara - RE Aoharu [Wish]","mods":"0","beatmapId":3980098,"ppOld":227,"ppNew":224},{"title":"yanaginagi - Yukitoki (TV Size) [OniJAM's Oni]","mods":"64","beatmapId":310380,"ppOld":203,"ppNew":220},{"title":"Hatsune Miku - Atama no Taisou [inaba's Taiko]","mods":"0","beatmapId":131290,"ppOld":219,"ppNew":217},{"title":"PinocchioP - Tonchinkan Feast feat. Hatsune Miku [Banketto]","mods":"0","beatmapId":3592637,"ppOld":216,"ppNew":215},{"title":"Hatsune Miku - Atama no Taisou [Love's Taiko]","mods":"0","beatmapId":131291,"ppOld":216,"ppNew":214},{"title":"Mischievous*Straight - To the Shining MiLie [Mischievous Oni]","mods":"0","beatmapId":4006190,"ppOld":207,"ppNew":214},{"title":"TUYU - Itsuka Otona ni Nareru to Ii ne. [Obsessive]","mods":"0","beatmapId":3673695,"ppOld":197,"ppNew":209},{"title":"Mitsukiyo - Hifumi Daisuki ~Raytoly Futurecore Remix~ [I Love Hifumi]","mods":"0","beatmapId":3716953,"ppOld":210,"ppNew":208},{"title":"sasakure.UK feat. Shirakami Fubuki - KINGWORLD [KING ONI]","mods":"0","beatmapId":3654236,"ppOld":209,"ppNew":206},{"title":"Creepy Nuts - Bling-Bang-Bang-Born (7_7 bootleg) [Inner Oni]","mods":"0","beatmapId":4500862,"ppOld":205,"ppNew":204},{"title":"Halv - Susano Habakiri [Inner Oni]","mods":"0","beatmapId":4488210,"ppOld":201,"ppNew":200},{"title":"xi - FREEDOM DiVE [Ono's Taiko Inner Oni]","mods":"1","beatmapId":161274,"ppOld":204,"ppNew":199},{"title":"ZUTOMAYO - Time Left (TV Size) [ETERNITY DEVIL]","mods":"0","beatmapId":3864316,"ppOld":189,"ppNew":192},{"title":"Hoshimachi Suisei - GHOST [Glistening Silhouette]","mods":"0","beatmapId":2997994,"ppOld":188,"ppNew":185},{"title":"MAXIMUM THE HORMONE - Hawatari 2-Oku Centi (TV Size) [2199'S INNER DEVIL]","mods":"0","beatmapId":3854451,"ppOld":185,"ppNew":184},{"title":"bibuko - Reizouko Mitara Pudding ga Nai [Alu's Taiko Oni]","mods":"0","beatmapId":256020,"ppOld":174,"ppNew":174},{"title":"CyoucyoP feat.Hatsune Miku - End of the World [Inner Oni]","mods":"0","beatmapId":506018,"ppOld":169,"ppNew":169},{"title":"t+pazolite - Tempestissimo [1811's Inner Oni]","mods":"0","beatmapId":2561042,"ppOld":160,"ppNew":159},{"title":"Nanaki feat.GUMI - Mousou Kajitsu [Delusional Fantasy]","mods":"0","beatmapId":1273614,"ppOld":161,"ppNew":158},{"title":"Mitsukiyo - Unwelcome School (t+pazolite Remix) [Let's Go!!!]","mods":"0","beatmapId":3762027,"ppOld":157,"ppNew":156},{"title":"UNDEAD CORPORATION - Yoru Naku Usagi wa Yume o Miru [Midnaait's Oni]","mods":"0","beatmapId":388464,"ppOld":158,"ppNew":155},{"title":"Camellia - #1f1e33 (#00102g version) [#00d4rk]","mods":"0","beatmapId":3112235,"ppOld":146,"ppNew":155},{"title":"TJ.hangneil - Apollo [Zeth's Inner Oni]","mods":"0","beatmapId":3558252,"ppOld":152,"ppNew":152},{"title":"Creepy Nuts - Otonoke (TV Size) [Oni]","mods":"0","beatmapId":4808641,"ppOld":140,"ppNew":152},{"title":"linear ring - lovely, lovely minute [Inner Oni]","mods":"0","beatmapId":3942500,"ppOld":135,"ppNew":150},{"title":"Hei Shou De Yu Tou - o i i a i o o o o o i a i [meow]","mods":"0","beatmapId":4222869,"ppOld":129,"ppNew":139},{"title":"UNDEAD CORPORATION - Embraced by the Flame [Inner Oni]","mods":"0","beatmapId":3607886,"ppOld":138,"ppNew":136},{"title":"ETIA. - Singularity [Raytoly's If You Can]","mods":"0","beatmapId":2443643,"ppOld":136,"ppNew":135},{"title":"HHHxMMxST - Oboro (KTFM Bootleg Remix) [Starless Night]","mods":"0","beatmapId":4358948,"ppOld":131,"ppNew":130},{"title":"Hoshimachi Suisei - KAKERO (PiEa's Bootleg J - CORE REMIX) [INTO THE COMET!!]","mods":"0","beatmapId":3332692,"ppOld":124,"ppNew":126},{"title":"cosMo@BousouP feat. Hatsune Miku - YAMINABE!!!! [MASTER]","mods":"0","beatmapId":4094667,"ppOld":112,"ppNew":120},{"title":"uma vs. Morimori Atsushi - Re: End of a Dream [Finality]","mods":"0","beatmapId":3911679,"ppOld":119,"ppNew":118},{"title":"xi - FREEDOM DiVE [Hayashi's Taiko Oni]","mods":"0","beatmapId":132914,"ppOld":99,"ppNew":97},{"title":"MAXIMUM THE HORMONE - Hawatari 2-Oku Centi (TV Size) [FOX DEVIL]","mods":"0","beatmapId":3854325,"ppOld":84,"ppNew":95},{"title":"Toby Fox - Dialtone [[[HYPERLINK BLOCKED]]]","mods":"1104","beatmapId":3701321,"ppOld":74,"ppNew":83},{"title":"MAXIMUM THE HORMONE - Hawatari 2-Oku Centi (TV Size) [UONE'S BLOOD DEVIL]","mods":"0","beatmapId":3854626,"ppOld":73,"ppNew":75},{"title":"TRUE - Sincerely [Amor]","mods":"0","beatmapId":1518386,"ppOld":35,"ppNew":39}]