{"93":{"maxcombo":792,"statistics":{"count_100":21,"count_300":423,"count_50":5,"count_geki":604,"count_katu":181,"count_miss":8},"user_id":8988941,"score_id":262813484,"rank":"A","pp":32.0478},"94":{"maxcombo":566,"statistics":{"count_100":14,"count_300":458,"count_50":0,"count_geki":596,"count_katu":164,"count_miss":10},"user_id":4143939,"score_id":155420534,"rank":"A","pp":34.8692},"98":{"maxcombo":704,"statistics":{"count_100":6,"count_300":324,"count_50":1,"count_geki":856,"count_katu":53,"count_miss":2},"user_id":613207,"score_id":202611853,"rank":"S","pp":50.6267},"96.5":{"maxcombo":756,"statistics":{"count_100":11,"count_300":341,"count_50":1,"count_geki":790,"count_katu":96,"count_miss":3},"user_id":9253574,"score_id":280868063,"rank":"S","pp":45.1882},"96.2":{"maxcombo":1365,"statistics":{"count_100":8,"count_300":451,"count_50":0,"count_geki":660,"count_katu":122,"count_miss":1},"user_id":7295895,"score_id":249399356,"rank":"S","pp":42.241},"96.6":{"maxcombo":1049,"statistics":{"count_100":6,"count_300":438,"count_50":0,"count_geki":693,"count_katu":102,"count_miss":3},"user_id":10195551,"score_id":547752177,"rank":"S","pp":44.1744},"94.4":{"maxcombo":1415,"statistics":{"count_100":8,"count_300":456,"count_50":3,"count_geki":592,"count_katu":182,"count_miss":1},"user_id":3194700,"score_id":85957956,"rank":"A","pp":35.8673}}