{"91":{"maxcombo":291,"statistics":{"count_100":98,"count_300":540,"count_50":null,"count_geki":null,"count_katu":null,"count_miss":9},"user_id":2285127,"score_id":91003358,"rank":"B","pp":63.2921},"98.8":{"maxcombo":647,"statistics":{"count_100":15,"count_300":632,"count_50":null,"count_geki":null,"count_katu":null,"count_miss":0},"user_id":2009008,"score_id":75452207,"rank":"S","pp":106.889},"97.5":{"maxcombo":647,"statistics":{"count_100":32,"count_300":615,"count_50":null,"count_geki":null,"count_katu":null,"count_miss":0},"user_id":38856,"score_id":69882371,"rank":"S","pp":99.3778},"97.4":{"maxcombo":472,"statistics":{"count_100":31,"count_300":615,"count_50":null,"count_geki":null,"count_katu":null,"count_miss":1},"user_id":4267507,"score_id":115460397,"rank":"A","pp":98.0203},"97.7":{"maxcombo":647,"statistics":{"count_100":29,"count_300":618,"count_50":null,"count_geki":null,"count_katu":null,"count_miss":0},"user_id":26560165,"score_id":168346103,"rank":"S","pp":100.658},"95.5":{"maxcombo":647,"statistics":{"count_100":57,"count_300":590,"count_50":null,"count_geki":null,"count_katu":null,"count_miss":0},"user_id":1617862,"score_id":115672566,"rank":"S","pp":89.4101},"95.2":{"maxcombo":647,"statistics":{"count_100":61,"count_300":586,"count_50":null,"count_geki":null,"count_katu":null,"count_miss":0},"user_id":1352808,"score_id":73423488,"rank":"S","pp":87.9259},"93.1":{"maxcombo":245,"statistics":{"count_100":76,"count_300":565,"count_50":null,"count_geki":null,"count_katu":null,"count_miss":6},"user_id":1855082,"score_id":71987259,"rank":"B","pp":73.6837},"97.3":{"maxcombo":340,"statistics":{"count_100":22,"count_300":619,"count_50":null,"count_geki":null,"count_katu":null,"count_miss":6},"user_id":1872256,"score_id":106198884,"rank":"A","pp":93.2042},"96.2":{"maxcombo":647,"statistics":{"count_100":48,"count_300":599,"count_50":null,"count_geki":null,"count_katu":null,"count_miss":0},"user_id":1012669,"score_id":118187090,"rank":"S","pp":92.8582},"97.1":{"maxcombo":586,"statistics":{"count_100":35,"count_300":611,"count_50":null,"count_geki":null,"count_katu":null,"count_miss":1},"user_id":6998676,"score_id":168151365,"rank":"A","pp":96.3552},"92.6":{"maxcombo":251,"statistics":{"count_100":55,"count_300":572,"count_50":null,"count_geki":null,"count_katu":null,"count_miss":20},"user_id":406289,"score_id":88354913,"rank":"B","pp":62.1638},"91.5":{"maxcombo":240,"statistics":{"count_100":97,"count_300":544,"count_50":null,"count_geki":null,"count_katu":null,"count_miss":6},"user_id":724712,"score_id":69681800,"rank":"B","pp":67.4123},"92.5":{"maxcombo":297,"statistics":{"count_100":71,"count_300":563,"count_50":null,"count_geki":null,"count_katu":null,"count_miss":13},"user_id":465581,"score_id":108915014,"rank":"B","pp":65.911},"90.8":{"maxcombo":397,"statistics":{"count_100":113,"count_300":531,"count_50":null,"count_geki":null,"count_katu":null,"count_miss":3},"user_id":1997410,"score_id":74700276,"rank":"B","pp":66.9493},"94.8":{"maxcombo":243,"statistics":{"count_100":51,"count_300":588,"count_50":null,"count_geki":null,"count_katu":null,"count_miss":8},"user_id":3733557,"score_id":143931820,"rank":"A","pp":79.0867},"92.3":{"maxcombo":247,"statistics":{"count_100":55,"count_300":570,"count_50":null,"count_geki":null,"count_katu":null,"count_miss":22},"user_id":1075383,"score_id":81885426,"rank":"B","pp":59.8936},"95.6":{"maxcombo":395,"statistics":{"count_100":40,"count_300":599,"count_50":null,"count_geki":null,"count_katu":null,"count_miss":8},"user_id":7240612,"score_id":123964617,"rank":"A","pp":83.0185},"93.5":{"maxcombo":314,"statistics":{"count_100":56,"count_300":577,"count_50":null,"count_geki":null,"count_katu":null,"count_miss":14},"user_id":2112694,"score_id":138472960,"rank":"B","pp":69.1908},"93.9":{"maxcombo":239,"statistics":{"count_100":62,"count_300":577,"count_50":null,"count_geki":null,"count_katu":null,"count_miss":8},"user_id":2808718,"score_id":95345747,"rank":"B","pp":75.3674},"92.7":{"maxcombo":216,"statistics":{"count_100":70,"count_300":565,"count_50":null,"count_geki":null,"count_katu":null,"count_miss":12},"user_id":15313486,"score_id":162893713,"rank":"B","pp":67.4733},"87.8":{"maxcombo":211,"statistics":{"count_100":129,"count_300":504,"count_50":null,"count_geki":null,"count_katu":null,"count_miss":14},"user_id":6657701,"score_id":117543478,"rank":"C","pp":50.1519}}