{"99.4":{"maxcombo":392,"statistics":{"count_100":4,"count_300":388,"count_50":null,"count_geki":null,"count_katu":null,"count_miss":0},"user_id":6387858,"score_id":140748324,"rank":"S","pp":74.6423},"97.7":{"maxcombo":392,"statistics":{"count_100":18,"count_300":374,"count_50":null,"count_geki":null,"count_katu":null,"count_miss":0},"user_id":8588047,"score_id":155939628,"rank":"S","pp":67.2613},"97.9":{"maxcombo":392,"statistics":{"count_100":16,"count_300":376,"count_50":null,"count_geki":null,"count_katu":null,"count_miss":0},"user_id":9470190,"score_id":133063724,"rank":"S","pp":68.2643},"97.3":{"maxcombo":215,"statistics":{"count_100":19,"count_300":372,"count_50":null,"count_geki":null,"count_katu":null,"count_miss":1},"user_id":9354977,"score_id":147437300,"rank":"A","pp":64.8671},"97.1":{"maxcombo":270,"statistics":{"count_100":20,"count_300":371,"count_50":null,"count_geki":null,"count_katu":null,"count_miss":1},"user_id":3695196,"score_id":117391622,"rank":"A","pp":64.3859},"96.9":{"maxcombo":392,"statistics":{"count_100":24,"count_300":368,"count_50":null,"count_geki":null,"count_katu":null,"count_miss":0},"user_id":15471891,"score_id":159239972,"rank":"S","pp":64.3498},"94.1":{"maxcombo":194,"statistics":{"count_100":30,"count_300":354,"count_50":null,"count_geki":null,"count_katu":null,"count_miss":8},"user_id":13570232,"score_id":158319146,"rank":"A","pp":48.6162},"94.3":{"maxcombo":261,"statistics":{"count_100":26,"count_300":357,"count_50":null,"count_geki":null,"count_katu":null,"count_miss":9},"user_id":9010535,"score_id":131848514,"rank":"A","pp":48.716},"96.8":{"maxcombo":203,"statistics":{"count_100":11,"count_300":374,"count_50":null,"count_geki":null,"count_katu":null,"count_miss":7},"user_id":11540570,"score_id":181597460,"rank":"A","pp":58.0903},"94.8":{"maxcombo":163,"statistics":{"count_100":18,"count_300":363,"count_50":null,"count_geki":null,"count_katu":null,"count_miss":11},"user_id":8428012,"score_id":161902210,"rank":"A","pp":49.0072},"95.5":{"maxcombo":189,"statistics":{"count_100":23,"count_300":363,"count_50":null,"count_geki":null,"count_katu":null,"count_miss":6},"user_id":6503338,"score_id":142645794,"rank":"A","pp":54.4387},"95.6":{"maxcombo":390,"statistics":{"count_100":30,"count_300":360,"count_50":null,"count_geki":null,"count_katu":null,"count_miss":2},"user_id":6027348,"score_id":124548459,"rank":"A","pp":58.0473},"92.4":{"maxcombo":124,"statistics":{"count_100":43,"count_300":341,"count_50":null,"count_geki":null,"count_katu":null,"count_miss":8},"user_id":4365910,"score_id":118622823,"rank":"B","pp":43.9397},"92.8":{"maxcombo":88,"statistics":{"count_100":42,"count_300":343,"count_50":null,"count_geki":null,"count_katu":null,"count_miss":7},"user_id":4220427,"score_id":120982858,"rank":"B","pp":45.6453},"98.2":{"maxcombo":392,"statistics":{"count_100":14,"count_300":378,"count_50":null,"count_geki":null,"count_katu":null,"count_miss":0},"user_id":7906381,"score_id":131636807,"rank":"S","pp":69.284},"94.6":{"maxcombo":162,"statistics":{"count_100":28,"count_300":357,"count_50":null,"count_geki":null,"count_katu":null,"count_miss":7},"user_id":4465572,"score_id":118533031,"rank":"A","pp":50.8581}}