{"99":{"maxcombo":661,"statistics":{"count_100":150,"count_300":685,"count_50":700,"count_geki":null,"count_katu":9,"count_miss":6},"user_id":6272800,"score_id":155513189,"rank":"S","pp":47.4208},"100":{"maxcombo":841,"statistics":{"count_100":150,"count_300":691,"count_50":709,"count_geki":null,"count_katu":0,"count_miss":0},"user_id":3534885,"score_id":201066928,"rank":"X","pp":72.8186},"98.5":{"maxcombo":698,"statistics":{"count_100":149,"count_300":688,"count_50":691,"count_geki":null,"count_katu":18,"count_miss":4},"user_id":2924813,"score_id":177719376,"rank":"S","pp":51.3371},"99.9":{"maxcombo":841,"statistics":{"count_100":150,"count_300":691,"count_50":708,"count_geki":null,"count_katu":1,"count_miss":0},"user_id":2514521,"score_id":146393215,"rank":"S","pp":72.5606},"99.8":{"maxcombo":841,"statistics":{"count_100":150,"count_300":691,"count_50":706,"count_geki":null,"count_katu":3,"count_miss":0},"user_id":1245012,"score_id":76208159,"rank":"S","pp":72.0468},"99.6":{"maxcombo":841,"statistics":{"count_100":150,"count_300":691,"count_50":703,"count_geki":null,"count_katu":6,"count_miss":0},"user_id":429666,"score_id":125667143,"rank":"S","pp":71.2817},"99.7":{"maxcombo":841,"statistics":{"count_100":150,"count_300":691,"count_50":705,"count_geki":null,"count_katu":4,"count_miss":0},"user_id":5154060,"score_id":155570616,"rank":"S","pp":71.7911},"99.3":{"maxcombo":712,"statistics":{"count_100":150,"count_300":688,"count_50":702,"count_geki":null,"count_katu":7,"count_miss":3},"user_id":5185717,"score_id":143453275,"rank":"S","pp":56.1364},"99.5":{"maxcombo":712,"statistics":{"count_100":150,"count_300":690,"count_50":703,"count_geki":null,"count_katu":6,"count_miss":1},"user_id":164857,"score_id":152464689,"rank":"S","pp":60.3045},"99.4":{"maxcombo":824,"statistics":{"count_100":150,"count_300":690,"count_50":702,"count_geki":null,"count_katu":7,"count_miss":1},"user_id":2759658,"score_id":216334091,"rank":"S","pp":67.5397},"99.2":{"maxcombo":725,"statistics":{"count_100":150,"count_300":686,"count_50":702,"count_geki":null,"count_katu":7,"count_miss":5},"user_id":3716389,"score_id":148429077,"rank":"S","pp":53.2072},"99.1":{"maxcombo":645,"statistics":{"count_100":150,"count_300":685,"count_50":702,"count_geki":null,"count_katu":7,"count_miss":6},"user_id":192863,"score_id":73047664,"rank":"S","pp":46.8345}}