{"100":{"maxcombo":428,"statistics":{"count_100":10,"count_300":418,"count_50":32,"count_geki":null,"count_katu":0,"count_miss":0},"user_id":4479729,"score_id":215184632,"rank":"X","pp":472.164},"99.7":{"maxcombo":428,"statistics":{"count_100":10,"count_300":418,"count_50":31,"count_geki":null,"count_katu":1,"count_miss":0},"user_id":17578266,"score_id":208585652,"rank":"S","pp":466.547},"99.1":{"maxcombo":394,"statistics":{"count_100":10,"count_300":415,"count_50":31,"count_geki":null,"count_katu":1,"count_miss":3},"user_id":9626549,"score_id":213822542,"rank":"S","pp":384.405},"98.4":{"maxcombo":369,"statistics":{"count_100":10,"count_300":412,"count_50":31,"count_geki":null,"count_katu":1,"count_miss":6},"user_id":14489248,"score_id":217531612,"rank":"S","pp":321.042},"97.8":{"maxcombo":312,"statistics":{"count_100":10,"count_300":408,"count_50":32,"count_geki":null,"count_katu":0,"count_miss":10},"user_id":14510301,"score_id":213464950,"rank":"A","pp":239.596},"99.3":{"maxcombo":399,"statistics":{"count_100":10,"count_300":416,"count_50":31,"count_geki":null,"count_katu":1,"count_miss":2},"user_id":21347411,"score_id":217550351,"rank":"S","pp":405.164},"96.7":{"maxcombo":243,"statistics":{"count_100":10,"count_300":404,"count_50":31,"count_geki":null,"count_katu":1,"count_miss":14},"user_id":19423459,"score_id":208728742,"rank":"A","pp":163.32},"98.9":{"maxcombo":307,"statistics":{"count_100":10,"count_300":414,"count_50":31,"count_geki":null,"count_katu":1,"count_miss":4},"user_id":23130846,"score_id":215076067,"rank":"S","pp":301.738},"96.5":{"maxcombo":182,"statistics":{"count_100":10,"count_300":403,"count_50":31,"count_geki":null,"count_katu":1,"count_miss":15},"user_id":25377492,"score_id":216579895,"rank":"A","pp":124.168},"95.4":{"maxcombo":113,"statistics":{"count_100":10,"count_300":397,"count_50":32,"count_geki":null,"count_katu":0,"count_miss":21},"user_id":12990538,"score_id":217407189,"rank":"A","pp":66.3735}}