[{"count":2.3,"cover":"https://assets.ppy.sh/beatmaps/252901/covers/list.jpg?1622081203","id":252901,"artist":"yuikonnu","title":"Chikyuu Saigo no Kokuhaku wo","ranked_date":"2018-04-30T23:19:05Z"},{"count":1.8,"cover":"https://assets.ppy.sh/beatmaps/364908/covers/list.jpg?1622094933","id":364908,"artist":"yuikonnu","title":"Natsu no Owari, Koi no Hajimari","ranked_date":"2019-02-19T20:44:50Z"},{"count":1.4,"cover":"https://assets.ppy.sh/beatmaps/291996/covers/list.jpg?0","id":291996,"artist":"Hyadain","title":"Hyadain no Joujou Yuujou","ranked_date":null},{"count":1.4,"cover":"https://assets.ppy.sh/beatmaps/736379/covers/list.jpg?1520540196","id":736379,"artist":"BNK48","title":"Koisuru Fortune Cookie","ranked_date":null},{"count":1,"cover":"https://assets.ppy.sh/beatmaps/309442/covers/list.jpg?0","id":309442,"artist":"Senya","title":"Yureru Koi wa Nami no Gotoku","ranked_date":null},{"count":1,"cover":"https://assets.ppy.sh/beatmaps/309443/covers/list.jpg?0","id":309443,"artist":"IA","title":"Heisei Catalysm","ranked_date":null},{"count":1,"cover":"https://assets.ppy.sh/beatmaps/419387/covers/list.jpg?1622100185","id":419387,"artist":"Sakuzyo","title":"Imprinting","ranked_date":"2019-04-15T17:19:52Z"},{"count":1,"cover":"https://assets.ppy.sh/beatmaps/460626/covers/list.jpg?1464275230","id":460626,"artist":"MIDI","title":"Piano Beatmap Set","ranked_date":null},{"count":1,"cover":"https://assets.ppy.sh/beatmaps/463826/covers/list.jpg?1622104557","id":463826,"artist":"Suzumu","title":"Kakumeisei ousama densenbyou","ranked_date":"2018-05-27T23:18:29Z"},{"count":1,"cover":"https://assets.ppy.sh/beatmaps/477965/covers/list.jpg?1467722558","id":477965,"artist":"yuikonnu","title":"The Name of the Sin","ranked_date":null},{"count":1,"cover":"https://assets.ppy.sh/beatmaps/503520/covers/list.jpg?1472737847","id":503520,"artist":"a_hisa","title":"Kreutzer","ranked_date":null},{"count":1,"cover":"https://assets.ppy.sh/beatmaps/945295/covers/list.jpg?1669264038","id":945295,"artist":"Dormir","title":"Sayonara Trip","ranked_date":"2022-11-25T15:25:27Z"},{"count":0.8,"cover":"https://assets.ppy.sh/beatmaps/2109235/covers/list.jpg?1720463469","id":2109235,"artist":"Christell","title":"Dubidubidu","ranked_date":null},{"count":0.6,"cover":"https://assets.ppy.sh/beatmaps/397749/covers/list.jpg?1645776582","id":397749,"artist":"Kano","title":"Dear Brave","ranked_date":null},{"count":0.5,"cover":"https://assets.ppy.sh/beatmaps/640271/covers/list.jpg?1622121873","id":640271,"artist":"Yuzuki Risa","title":"Toumei na Kioku no Kazaana","ranked_date":"2020-05-26T02:31:27Z"}]