{"84":{"maxcombo":236,"statistics":{"count_100":80,"count_300":289,"count_50":3,"count_geki":null,"count_katu":null,"count_miss":4},"user_id":14329041,"score_id":4341873850,"rank":"C","pp":39.6713},"85":{"maxcombo":296,"statistics":{"count_100":80,"count_300":293,"count_50":0,"count_geki":null,"count_katu":null,"count_miss":3},"user_id":8305003,"score_id":2919836893,"rank":"C","pp":50.707},"87":{"maxcombo":541,"statistics":{"count_100":73,"count_300":303,"count_50":0,"count_geki":null,"count_katu":null,"count_miss":0},"user_id":18910947,"score_id":4499580659,"rank":"A","pp":93.9908},"96":{"maxcombo":258,"statistics":{"count_100":18,"count_300":355,"count_50":0,"count_geki":null,"count_katu":null,"count_miss":3},"user_id":5462329,"score_id":4452542596,"rank":"A","pp":66.0131},"97":{"maxcombo":415,"statistics":{"count_100":9,"count_300":362,"count_50":0,"count_geki":null,"count_katu":null,"count_miss":5},"user_id":21157803,"score_id":3923587794,"rank":"A","pp":92.1296},"98":{"maxcombo":544,"statistics":{"count_100":11,"count_300":365,"count_50":0,"count_geki":null,"count_katu":null,"count_miss":0},"user_id":13941898,"score_id":4384729821,"rank":"S","pp":142.309},"99.6":{"maxcombo":544,"statistics":{"count_100":2,"count_300":374,"count_50":0,"count_geki":null,"count_katu":null,"count_miss":0},"user_id":9986143,"score_id":3057799124,"rank":"S","pp":178.991},"99.1":{"maxcombo":544,"statistics":{"count_100":5,"count_300":371,"count_50":0,"count_geki":null,"count_katu":null,"count_miss":0},"user_id":14369666,"score_id":4550457389,"rank":"S","pp":164.034},"99.2":{"maxcombo":543,"statistics":{"count_100":4,"count_300":372,"count_50":0,"count_geki":null,"count_katu":null,"count_miss":0},"user_id":3026809,"score_id":3024633454,"rank":"S","pp":164.28},"97.8":{"maxcombo":544,"statistics":{"count_100":12,"count_300":364,"count_50":0,"count_geki":null,"count_katu":null,"count_miss":0},"user_id":25499979,"score_id":4159701542,"rank":"S","pp":139.518},"96.8":{"maxcombo":539,"statistics":{"count_100":18,"count_300":358,"count_50":0,"count_geki":null,"count_katu":null,"count_miss":0},"user_id":16997915,"score_id":4014671936,"rank":"S","pp":125.434},"98.2":{"maxcombo":543,"statistics":{"count_100":10,"count_300":366,"count_50":0,"count_geki":null,"count_katu":null,"count_miss":0},"user_id":13382075,"score_id":4659908265,"rank":"S","pp":145.116},"96.1":{"maxcombo":498,"statistics":{"count_100":20,"count_300":355,"count_50":0,"count_geki":null,"count_katu":null,"count_miss":1},"user_id":13935618,"score_id":3335566288,"rank":"A","pp":109.274},"94.6":{"maxcombo":544,"statistics":{"count_100":30,"count_300":346,"count_50":0,"count_geki":null,"count_katu":null,"count_miss":0},"user_id":24105628,"score_id":4291096888,"rank":"S","pp":111.79},"95.9":{"maxcombo":472,"statistics":{"count_100":23,"count_300":353,"count_50":0,"count_geki":null,"count_katu":null,"count_miss":0},"user_id":16741703,"score_id":4480160268,"rank":"S","pp":103.234},"95.2":{"maxcombo":541,"statistics":{"count_100":27,"count_300":349,"count_50":0,"count_geki":null,"count_katu":null,"count_miss":0},"user_id":5618077,"score_id":3669998270,"rank":"S","pp":113.906},"95.1":{"maxcombo":500,"statistics":{"count_100":26,"count_300":349,"count_50":0,"count_geki":null,"count_katu":null,"count_miss":1},"user_id":23036555,"score_id":4003889012,"rank":"A","pp":102.813},"88.4":{"maxcombo":544,"statistics":{"count_100":65,"count_300":311,"count_50":0,"count_geki":null,"count_katu":null,"count_miss":0},"user_id":21915859,"score_id":4207526736,"rank":"A","pp":96.6617},"93.5":{"maxcombo":541,"statistics":{"count_100":35,"count_300":340,"count_50":0,"count_geki":null,"count_katu":null,"count_miss":1},"user_id":8156745,"score_id":3812218804,"rank":"A","pp":102.681},"93.9":{"maxcombo":543,"statistics":{"count_100":34,"count_300":342,"count_50":0,"count_geki":null,"count_katu":null,"count_miss":0},"user_id":8928429,"score_id":3893277289,"rank":"S","pp":108.683},"87.9":{"maxcombo":502,"statistics":{"count_100":64,"count_300":309,"count_50":2,"count_geki":null,"count_katu":null,"count_miss":1},"user_id":9480534,"score_id":4500945964,"rank":"B","pp":85.8604},"95.5":{"maxcombo":543,"statistics":{"count_100":25,"count_300":351,"count_50":0,"count_geki":null,"count_katu":null,"count_miss":0},"user_id":20438414,"score_id":3803431835,"rank":"S","pp":116.35},"89.8":{"maxcombo":436,"statistics":{"count_100":56,"count_300":319,"count_50":0,"count_geki":null,"count_katu":null,"count_miss":1},"user_id":14070648,"score_id":3778712924,"rank":"B","pp":79.0803},"93.3":{"maxcombo":442,"statistics":{"count_100":33,"count_300":340,"count_50":0,"count_geki":null,"count_katu":null,"count_miss":3},"user_id":15841440,"score_id":4133517266,"rank":"A","pp":82.3306},"96.7":{"maxcombo":363,"statistics":{"count_100":17,"count_300":358,"count_50":0,"count_geki":null,"count_katu":null,"count_miss":1},"user_id":10682590,"score_id":4174970976,"rank":"A","pp":91.9059},"95.8":{"maxcombo":440,"statistics":{"count_100":19,"count_300":354,"count_50":0,"count_geki":null,"count_katu":null,"count_miss":3},"user_id":17954352,"score_id":3884186891,"rank":"A","pp":92.8447},"91.9":{"maxcombo":506,"statistics":{"count_100":44,"count_300":331,"count_50":0,"count_geki":null,"count_katu":null,"count_miss":1},"user_id":20044581,"score_id":4092255631,"rank":"B","pp":93.1788},"89.6":{"maxcombo":542,"statistics":{"count_100":56,"count_300":318,"count_50":2,"count_geki":null,"count_katu":null,"count_miss":0},"user_id":14793057,"score_id":3730782957,"rank":"A","pp":98.0361},"91.3":{"maxcombo":378,"statistics":{"count_100":45,"count_300":328,"count_50":2,"count_geki":null,"count_katu":null,"count_miss":1},"user_id":12061235,"score_id":4306901613,"rank":"B","pp":72.3859},"87.8":{"maxcombo":490,"statistics":{"count_100":66,"count_300":308,"count_50":2,"count_geki":null,"count_katu":null,"count_miss":0},"user_id":25568539,"score_id":3853979903,"rank":"A","pp":84.0567},"84.6":{"maxcombo":444,"statistics":{"count_100":83,"count_300":290,"count_50":3,"count_geki":null,"count_katu":null,"count_miss":0},"user_id":10758766,"score_id":4079667549,"rank":"B","pp":73.5858},"96.6":{"maxcombo":247,"statistics":{"count_100":16,"count_300":358,"count_50":0,"count_geki":null,"count_katu":null,"count_miss":2},"user_id":14624338,"score_id":4668224008,"rank":"A","pp":70.7307},"96.2":{"maxcombo":543,"statistics":{"count_100":21,"count_300":355,"count_50":0,"count_geki":null,"count_katu":null,"count_miss":0},"user_id":13103839,"score_id":3778232605,"rank":"S","pp":121.395},"95.3":{"maxcombo":482,"statistics":{"count_100":25,"count_300":350,"count_50":0,"count_geki":null,"count_katu":null,"count_miss":1},"user_id":9010883,"score_id":3726241636,"rank":"A","pp":100.962},"86.9":{"maxcombo":347,"statistics":{"count_100":68,"count_300":304,"count_50":1,"count_geki":null,"count_katu":null,"count_miss":3},"user_id":7600588,"score_id":3345821046,"rank":"B","pp":59.3314},"89.9":{"maxcombo":256,"statistics":{"count_100":51,"count_300":321,"count_50":2,"count_geki":null,"count_katu":null,"count_miss":2},"user_id":12264687,"score_id":4445635890,"rank":"B","pp":50.8038},"96.9":{"maxcombo":185,"statistics":{"count_100":11,"count_300":361,"count_50":0,"count_geki":null,"count_katu":null,"count_miss":4},"user_id":17927966,"score_id":3643569974,"rank":"A","pp":60.2506},"93.4":{"maxcombo":360,"statistics":{"count_100":34,"count_300":340,"count_50":0,"count_geki":null,"count_katu":null,"count_miss":2},"user_id":17307877,"score_id":4155983756,"rank":"A","pp":73.0852},"75.6":{"maxcombo":387,"statistics":{"count_100":124,"count_300":242,"count_50":7,"count_geki":null,"count_katu":null,"count_miss":3},"user_id":22386204,"score_id":3846356050,"rank":"C","pp":53.8472},"79.5":{"maxcombo":354,"statistics":{"count_100":96,"count_300":266,"count_50":7,"count_geki":null,"count_katu":null,"count_miss":7},"user_id":23335360,"score_id":4436591349,"rank":"C","pp":41.5929},"90.5":{"maxcombo":234,"statistics":{"count_100":44,"count_300":325,"count_50":5,"count_geki":null,"count_katu":null,"count_miss":2},"user_id":17679107,"score_id":4093177908,"rank":"B","pp":47.445},"86.7":{"maxcombo":284,"statistics":{"count_100":66,"count_300":304,"count_50":0,"count_geki":null,"count_katu":null,"count_miss":6},"user_id":11418463,"score_id":3554539683,"rank":"B","pp":42.4828},"91.2":{"maxcombo":254,"statistics":{"count_100":45,"count_300":328,"count_50":1,"count_geki":null,"count_katu":null,"count_miss":2},"user_id":4082931,"score_id":2902575407,"rank":"B","pp":49.8823},"85.4":{"maxcombo":245,"statistics":{"count_100":74,"count_300":296,"count_50":4,"count_geki":null,"count_katu":null,"count_miss":2},"user_id":9502132,"score_id":3275383113,"rank":"C","pp":45.1268},"84.4":{"maxcombo":203,"statistics":{"count_100":75,"count_300":292,"count_50":3,"count_geki":null,"count_katu":null,"count_miss":6},"user_id":5276665,"score_id":3725481181,"rank":"C","pp":31.2327},"91.7":{"maxcombo":252,"statistics":{"count_100":36,"count_300":333,"count_50":1,"count_geki":null,"count_katu":null,"count_miss":6},"user_id":23545661,"score_id":3775357564,"rank":"B","pp":43.0954},"94.3":{"maxcombo":291,"statistics":{"count_100":26,"count_300":346,"count_50":0,"count_geki":null,"count_katu":null,"count_miss":4},"user_id":28049700,"score_id":4160762989,"rank":"A","pp":60.2422},"79.9":{"maxcombo":256,"statistics":{"count_100":105,"count_300":265,"count_50":3,"count_geki":null,"count_katu":null,"count_miss":3},"user_id":18411452,"score_id":4537443064,"rank":"C","pp":41.5656},"78.9":{"maxcombo":178,"statistics":{"count_100":110,"count_300":260,"count_50":0,"count_geki":null,"count_katu":null,"count_miss":6},"user_id":11296897,"score_id":4252833566,"rank":"C","pp":25.7972}}