{"84":{"maxcombo":190,"statistics":{"count_100":35,"count_300":121,"count_50":1,"count_geki":null,"count_katu":null,"count_miss":1},"user_id":34729276,"score_id":4685934359,"rank":"C","pp":129.548},"87":{"maxcombo":132,"statistics":{"count_100":25,"count_300":129,"count_50":1,"count_geki":null,"count_katu":null,"count_miss":3},"user_id":15241555,"score_id":3204835354,"rank":"B","pp":91.1193},"89":{"maxcombo":212,"statistics":{"count_100":26,"count_300":132,"count_50":0,"count_geki":null,"count_katu":null,"count_miss":0},"user_id":6548962,"score_id":3015308934,"rank":"A","pp":163.824},"91":{"maxcombo":213,"statistics":{"count_100":20,"count_300":137,"count_50":1,"count_geki":null,"count_katu":null,"count_miss":0},"user_id":18444718,"score_id":3598750971,"rank":"A","pp":171.695},"96":{"maxcombo":213,"statistics":{"count_100":8,"count_300":149,"count_50":1,"count_geki":null,"count_katu":null,"count_miss":0},"user_id":10581212,"score_id":4235421934,"rank":"S","pp":205.803},"97":{"maxcombo":213,"statistics":{"count_100":7,"count_300":151,"count_50":0,"count_geki":null,"count_katu":null,"count_miss":0},"user_id":7836113,"score_id":3308051791,"rank":"S","pp":218.579},"100":{"maxcombo":213,"statistics":{"count_100":0,"count_300":158,"count_50":0,"count_geki":null,"count_katu":null,"count_miss":0},"user_id":2388987,"score_id":3256990133,"rank":"X","pp":289.294},"99.5":{"maxcombo":213,"statistics":{"count_100":1,"count_300":157,"count_50":0,"count_geki":null,"count_katu":null,"count_miss":0},"user_id":29939315,"score_id":4541175784,"rank":"S","pp":274.985},"99.1":{"maxcombo":213,"statistics":{"count_100":2,"count_300":156,"count_50":0,"count_geki":null,"count_katu":null,"count_miss":0},"user_id":12050697,"score_id":3004191009,"rank":"S","pp":262.394},"98.7":{"maxcombo":213,"statistics":{"count_100":3,"count_300":155,"count_50":0,"count_geki":null,"count_katu":null,"count_miss":0},"user_id":9404433,"score_id":3067290041,"rank":"S","pp":251.309},"98.3":{"maxcombo":213,"statistics":{"count_100":4,"count_300":154,"count_50":0,"count_geki":null,"count_katu":null,"count_miss":0},"user_id":5906101,"score_id":3000591388,"rank":"S","pp":241.542},"97.8":{"maxcombo":213,"statistics":{"count_100":5,"count_300":153,"count_50":0,"count_geki":null,"count_katu":null,"count_miss":0},"user_id":6255494,"score_id":2943731658,"rank":"S","pp":232.926},"97.4":{"maxcombo":213,"statistics":{"count_100":6,"count_300":152,"count_50":0,"count_geki":null,"count_katu":null,"count_miss":0},"user_id":12565363,"score_id":2879260985,"rank":"S","pp":225.315},"97.2":{"maxcombo":213,"statistics":{"count_100":4,"count_300":152,"count_50":2,"count_geki":null,"count_katu":null,"count_miss":0},"user_id":10581921,"score_id":4691769299,"rank":"A","pp":221.186},"96.6":{"maxcombo":213,"statistics":{"count_100":8,"count_300":150,"count_50":0,"count_geki":null,"count_katu":null,"count_miss":0},"user_id":25181278,"score_id":4533574229,"rank":"S","pp":212.606},"97.3":{"maxcombo":213,"statistics":{"count_100":5,"count_300":152,"count_50":1,"count_geki":null,"count_katu":null,"count_miss":0},"user_id":21305103,"score_id":4292876669,"rank":"S","pp":223.283},"95.9":{"maxcombo":213,"statistics":{"count_100":7,"count_300":149,"count_50":2,"count_geki":null,"count_katu":null,"count_miss":0},"user_id":13490243,"score_id":3161785018,"rank":"A","pp":204.231},"95.3":{"maxcombo":213,"statistics":{"count_100":11,"count_300":147,"count_50":0,"count_geki":null,"count_katu":null,"count_miss":0},"user_id":9328141,"score_id":3137823894,"rank":"S","pp":198.329},"95.7":{"maxcombo":213,"statistics":{"count_100":10,"count_300":148,"count_50":0,"count_geki":null,"count_katu":null,"count_miss":0},"user_id":8622953,"score_id":3021752052,"rank":"S","pp":202.563},"96.2":{"maxcombo":213,"statistics":{"count_100":9,"count_300":149,"count_50":0,"count_geki":null,"count_katu":null,"count_miss":0},"user_id":11216818,"score_id":4391368445,"rank":"S","pp":207.297},"97.6":{"maxcombo":189,"statistics":{"count_100":4,"count_300":153,"count_50":0,"count_geki":null,"count_katu":null,"count_miss":1},"user_id":20776305,"score_id":4382816208,"rank":"A","pp":202.939},"94.5":{"maxcombo":212,"statistics":{"count_100":13,"count_300":145,"count_50":0,"count_geki":null,"count_katu":null,"count_miss":0},"user_id":30855938,"score_id":4597040817,"rank":"S","pp":190.185},"93.1":{"maxcombo":213,"statistics":{"count_100":15,"count_300":142,"count_50":1,"count_geki":null,"count_katu":null,"count_miss":0},"user_id":11809437,"score_id":4656328183,"rank":"A","pp":181.762},"98.1":{"maxcombo":192,"statistics":{"count_100":3,"count_300":154,"count_50":0,"count_geki":null,"count_katu":null,"count_miss":1},"user_id":6321608,"score_id":4049574860,"rank":"A","pp":213.066},"95.2":{"maxcombo":212,"statistics":{"count_100":10,"count_300":147,"count_50":1,"count_geki":null,"count_katu":null,"count_miss":0},"user_id":20392895,"score_id":4455140247,"rank":"S","pp":196.164},"92.7":{"maxcombo":213,"statistics":{"count_100":16,"count_300":141,"count_50":1,"count_geki":null,"count_katu":null,"count_miss":0},"user_id":26230221,"score_id":4312726541,"rank":"A","pp":179.445},"94.4":{"maxcombo":212,"statistics":{"count_100":12,"count_300":145,"count_50":1,"count_geki":null,"count_katu":null,"count_miss":0},"user_id":15083562,"score_id":3451192548,"rank":"S","pp":189.139},"96.4":{"maxcombo":198,"statistics":{"count_100":7,"count_300":150,"count_50":0,"count_geki":null,"count_katu":null,"count_miss":1},"user_id":15644924,"score_id":4534162855,"rank":"A","pp":190.314},"94.9":{"maxcombo":213,"statistics":{"count_100":12,"count_300":146,"count_50":0,"count_geki":null,"count_katu":null,"count_miss":0},"user_id":9883678,"score_id":3559474748,"rank":"S","pp":194.528},"90.2":{"maxcombo":212,"statistics":{"count_100":23,"count_300":135,"count_50":0,"count_geki":null,"count_katu":null,"count_miss":0},"user_id":7083042,"score_id":4581493284,"rank":"A","pp":168.192},"91.9":{"maxcombo":213,"statistics":{"count_100":19,"count_300":139,"count_50":0,"count_geki":null,"count_katu":null,"count_miss":0},"user_id":15019543,"score_id":3718409903,"rank":"A","pp":176.018},"93.6":{"maxcombo":213,"statistics":{"count_100":15,"count_300":143,"count_50":0,"count_geki":null,"count_katu":null,"count_miss":0},"user_id":31020631,"score_id":4692728682,"rank":"S","pp":185.183},"94.3":{"maxcombo":212,"statistics":{"count_100":11,"count_300":145,"count_50":2,"count_geki":null,"count_katu":null,"count_miss":0},"user_id":8684203,"score_id":4418831850,"rank":"A","pp":188.006},"91.5":{"maxcombo":211,"statistics":{"count_100":20,"count_300":138,"count_50":0,"count_geki":null,"count_katu":null,"count_miss":0},"user_id":15288185,"score_id":3738072631,"rank":"A","pp":172.432},"92.8":{"maxcombo":213,"statistics":{"count_100":17,"count_300":141,"count_50":0,"count_geki":null,"count_katu":null,"count_miss":0},"user_id":16656876,"score_id":4497525825,"rank":"A","pp":180.237},"90.7":{"maxcombo":212,"statistics":{"count_100":22,"count_300":136,"count_50":0,"count_geki":null,"count_katu":null,"count_miss":0},"user_id":18073472,"score_id":4479713503,"rank":"A","pp":169.783},"92.4":{"maxcombo":213,"statistics":{"count_100":18,"count_300":140,"count_50":0,"count_geki":null,"count_katu":null,"count_miss":0},"user_id":12167969,"score_id":3344385557,"rank":"A","pp":178.05},"91.1":{"maxcombo":210,"statistics":{"count_100":21,"count_300":137,"count_50":0,"count_geki":null,"count_katu":null,"count_miss":0},"user_id":8649653,"score_id":3140627276,"rank":"A","pp":169.925},"91.3":{"maxcombo":212,"statistics":{"count_100":18,"count_300":138,"count_50":2,"count_geki":null,"count_katu":null,"count_miss":0},"user_id":17568800,"score_id":3890540000,"rank":"A","pp":171.805},"94.6":{"maxcombo":192,"statistics":{"count_100":10,"count_300":146,"count_50":1,"count_geki":null,"count_katu":null,"count_miss":1},"user_id":23917353,"score_id":3905241982,"rank":"A","pp":168.538},"87.7":{"maxcombo":211,"statistics":{"count_100":29,"count_300":129,"count_50":0,"count_geki":null,"count_katu":null,"count_miss":0},"user_id":11819733,"score_id":4216137709,"rank":"A","pp":159.131},"95.6":{"maxcombo":212,"statistics":{"count_100":9,"count_300":148,"count_50":1,"count_geki":null,"count_katu":null,"count_miss":0},"user_id":24555881,"score_id":4262308242,"rank":"S","pp":200.275},"93.5":{"maxcombo":213,"statistics":{"count_100":14,"count_300":143,"count_50":1,"count_geki":null,"count_katu":null,"count_miss":0},"user_id":17659830,"score_id":4177566706,"rank":"S","pp":184.28},"93.2":{"maxcombo":212,"statistics":{"count_100":16,"count_300":142,"count_50":0,"count_geki":null,"count_katu":null,"count_miss":0},"user_id":18986066,"score_id":3926287914,"rank":"A","pp":181.701},"86.4":{"maxcombo":212,"statistics":{"count_100":27,"count_300":127,"count_50":4,"count_geki":null,"count_katu":null,"count_miss":0},"user_id":15587524,"score_id":3310607492,"rank":"A","pp":155.309},"89.8":{"maxcombo":213,"statistics":{"count_100":24,"count_300":134,"count_50":0,"count_geki":null,"count_katu":null,"count_miss":0},"user_id":10059410,"score_id":3159908239,"rank":"A","pp":167.539},"89.4":{"maxcombo":212,"statistics":{"count_100":25,"count_300":133,"count_50":0,"count_geki":null,"count_katu":null,"count_miss":0},"user_id":25159799,"score_id":4590373867,"rank":"A","pp":165.222},"92.6":{"maxcombo":212,"statistics":{"count_100":15,"count_300":141,"count_50":2,"count_geki":null,"count_katu":null,"count_miss":0},"user_id":6255235,"score_id":2977609670,"rank":"A","pp":177.669},"89.2":{"maxcombo":211,"statistics":{"count_100":23,"count_300":133,"count_50":2,"count_geki":null,"count_katu":null,"count_miss":0},"user_id":11387267,"score_id":4288302642,"rank":"A","pp":163.255},"85.6":{"maxcombo":212,"statistics":{"count_100":34,"count_300":124,"count_50":0,"count_geki":null,"count_katu":null,"count_miss":0},"user_id":23029779,"score_id":3923097341,"rank":"B","pp":153.919},"87.9":{"maxcombo":213,"statistics":{"count_100":26,"count_300":130,"count_50":2,"count_geki":null,"count_katu":null,"count_miss":0},"user_id":33104079,"score_id":4637547396,"rank":"A","pp":160.902},"86.9":{"maxcombo":213,"statistics":{"count_100":31,"count_300":127,"count_50":0,"count_geki":null,"count_katu":null,"count_miss":0},"user_id":11443677,"score_id":3280019444,"rank":"A","pp":158.262},"90.1":{"maxcombo":203,"statistics":{"count_100":22,"count_300":135,"count_50":1,"count_geki":null,"count_katu":null,"count_miss":0},"user_id":18681773,"score_id":4580662997,"rank":"A","pp":153.656},"86.7":{"maxcombo":198,"statistics":{"count_100":29,"count_300":127,"count_50":2,"count_geki":null,"count_katu":null,"count_miss":0},"user_id":13797850,"score_id":4062610240,"rank":"A","pp":140.281},"84.8":{"maxcombo":212,"statistics":{"count_100":31,"count_300":123,"count_50":4,"count_geki":null,"count_katu":null,"count_miss":0},"user_id":17556901,"score_id":3536738458,"rank":"B","pp":150.795},"88.5":{"maxcombo":212,"statistics":{"count_100":26,"count_300":131,"count_50":1,"count_geki":null,"count_katu":null,"count_miss":0},"user_id":16211627,"score_id":4544926966,"rank":"A","pp":161.951},"89.5":{"maxcombo":189,"statistics":{"count_100":22,"count_300":134,"count_50":1,"count_geki":null,"count_katu":null,"count_miss":1},"user_id":11184308,"score_id":4307035592,"rank":"B","pp":142.863},"91.8":{"maxcombo":188,"statistics":{"count_100":15,"count_300":140,"count_50":1,"count_geki":null,"count_katu":null,"count_miss":2},"user_id":8651904,"score_id":3689791946,"rank":"B","pp":144.225},"91.2":{"maxcombo":190,"statistics":{"count_100":18,"count_300":138,"count_50":1,"count_geki":null,"count_katu":null,"count_miss":1},"user_id":16173824,"score_id":3537985935,"rank":"B","pp":149.212},"93.7":{"maxcombo":180,"statistics":{"count_100":12,"count_300":144,"count_50":1,"count_geki":null,"count_katu":null,"count_miss":1},"user_id":19302682,"score_id":4015977409,"rank":"A","pp":154.69},"89.3":{"maxcombo":189,"statistics":{"count_100":20,"count_300":134,"count_50":3,"count_geki":null,"count_katu":null,"count_miss":1},"user_id":6730759,"score_id":3090188736,"rank":"B","pp":141.731},"90.6":{"maxcombo":213,"statistics":{"count_100":21,"count_300":136,"count_50":1,"count_geki":null,"count_katu":null,"count_miss":0},"user_id":17654450,"score_id":4300859496,"rank":"A","pp":170.039},"87.3":{"maxcombo":189,"statistics":{"count_100":27,"count_300":129,"count_50":0,"count_geki":null,"count_katu":null,"count_miss":2},"user_id":22058419,"score_id":4103766625,"rank":"B","pp":131.028},"93.4":{"maxcombo":187,"statistics":{"count_100":10,"count_300":144,"count_50":2,"count_geki":null,"count_katu":null,"count_miss":2},"user_id":19451467,"score_id":3972211128,"rank":"A","pp":150.948},"79.4":{"maxcombo":213,"statistics":{"count_100":45,"count_300":110,"count_50":3,"count_geki":null,"count_katu":null,"count_miss":0},"user_id":17422381,"score_id":3821117883,"rank":"C","pp":138.413},"84.5":{"maxcombo":192,"statistics":{"count_100":35,"count_300":122,"count_50":0,"count_geki":null,"count_katu":null,"count_miss":1},"user_id":16055609,"score_id":4645224371,"rank":"C","pp":132.042},"86.6":{"maxcombo":212,"statistics":{"count_100":28,"count_300":127,"count_50":3,"count_geki":null,"count_katu":null,"count_miss":0},"user_id":35751971,"score_id":4624792350,"rank":"A","pp":155.851},"85.4":{"maxcombo":190,"statistics":{"count_100":30,"count_300":125,"count_50":0,"count_geki":null,"count_katu":null,"count_miss":3},"user_id":18851521,"score_id":4677842187,"rank":"C","pp":118.366},"73.7":{"maxcombo":212,"statistics":{"count_100":61,"count_300":96,"count_50":1,"count_geki":null,"count_katu":null,"count_miss":0},"user_id":30680214,"score_id":4684160672,"rank":"C","pp":124.812},"89.9":{"maxcombo":189,"statistics":{"count_100":21,"count_300":135,"count_50":1,"count_geki":null,"count_katu":null,"count_miss":1},"user_id":11493606,"score_id":3686657401,"rank":"B","pp":144.179},"93.3":{"maxcombo":133,"statistics":{"count_100":10,"count_300":144,"count_50":1,"count_geki":null,"count_katu":null,"count_miss":3},"user_id":32779455,"score_id":4674918131,"rank":"A","pp":109.545},"85.3":{"maxcombo":185,"statistics":{"count_100":28,"count_300":125,"count_50":3,"count_geki":null,"count_katu":null,"count_miss":2},"user_id":14099760,"score_id":3242530970,"rank":"C","pp":123.663},"88.9":{"maxcombo":133,"statistics":{"count_100":22,"count_300":133,"count_50":1,"count_geki":null,"count_katu":null,"count_miss":2},"user_id":28789007,"score_id":4197839666,"rank":"B","pp":102.292},"16.6":{"maxcombo":0,"statistics":{"count_100":1,"count_300":0,"count_50":0,"count_geki":null,"count_katu":null,"count_miss":1},"user_id":36850192,"score_id":3688456070,"rank":"D","pp":76.7299},"82.2":{"maxcombo":177,"statistics":{"count_100":35,"count_300":118,"count_50":2,"count_geki":null,"count_katu":null,"count_miss":3},"user_id":12438274,"score_id":4043570407,"rank":"C","pp":105.521},"73.3":{"maxcombo":118,"statistics":{"count_100":58,"count_300":96,"count_50":3,"count_geki":null,"count_katu":null,"count_miss":1},"user_id":13314876,"score_id":4580889953,"rank":"C","pp":70.8583}}