{"99":{"maxcombo":960,"statistics":{"count_100":6,"count_300":508,"count_50":1,"count_geki":null,"count_katu":null,"count_miss":0},"user_id":1962731,"score_id":1779463276,"rank":"SH","pp":42.4939},"99.1":{"maxcombo":960,"statistics":{"count_100":5,"count_300":509,"count_50":1,"count_geki":null,"count_katu":null,"count_miss":0},"user_id":4648815,"score_id":2157637815,"rank":"SH","pp":44.2739},"99.7":{"maxcombo":960,"statistics":{"count_100":2,"count_300":513,"count_50":0,"count_geki":null,"count_katu":null,"count_miss":0},"user_id":1817514,"score_id":3720116791,"rank":"SH","pp":50.9126},"99.4":{"maxcombo":960,"statistics":{"count_100":4,"count_300":511,"count_50":0,"count_geki":null,"count_katu":null,"count_miss":0},"user_id":3160044,"score_id":3771902844,"rank":"SH","pp":47.5757}}