{"93":{"maxcombo":480,"statistics":{"count_100":30,"count_300":280,"count_50":2,"count_geki":null,"count_katu":null,"count_miss":0},"user_id":28904054,"score_id":4700444961,"rank":"A","pp":73.4895},"97":{"maxcombo":481,"statistics":{"count_100":14,"count_300":298,"count_50":0,"count_geki":null,"count_katu":null,"count_miss":0},"user_id":23981592,"score_id":4693391428,"rank":"S","pp":90.2015},"99.3":{"maxcombo":481,"statistics":{"count_100":3,"count_300":309,"count_50":0,"count_geki":null,"count_katu":null,"count_miss":0},"user_id":16702879,"score_id":4693338784,"rank":"S","pp":118.863},"98.2":{"maxcombo":481,"statistics":{"count_100":8,"count_300":304,"count_50":0,"count_geki":null,"count_katu":null,"count_miss":0},"user_id":4851571,"score_id":4693199384,"rank":"S","pp":102.293},"98.6":{"maxcombo":481,"statistics":{"count_100":5,"count_300":306,"count_50":1,"count_geki":null,"count_katu":null,"count_miss":0},"user_id":30495133,"score_id":4697352602,"rank":"S","pp":107.126},"96.1":{"maxcombo":444,"statistics":{"count_100":14,"count_300":295,"count_50":2,"count_geki":null,"count_katu":null,"count_miss":1},"user_id":18111230,"score_id":4694423271,"rank":"A","pp":76.0428},"91.5":{"maxcombo":476,"statistics":{"count_100":36,"count_300":273,"count_50":3,"count_geki":null,"count_katu":null,"count_miss":0},"user_id":35966792,"score_id":3728876266,"rank":"A","pp":70.1754},"95.7":{"maxcombo":363,"statistics":{"count_100":17,"count_300":293,"count_50":0,"count_geki":null,"count_katu":null,"count_miss":2},"user_id":19941169,"score_id":4696095467,"rank":"A","pp":62.3802},"98.7":{"maxcombo":262,"statistics":{"count_100":3,"count_300":307,"count_50":0,"count_geki":null,"count_katu":null,"count_miss":2},"user_id":12380579,"score_id":4694253912,"rank":"A","pp":72.4306},"97.2":{"maxcombo":481,"statistics":{"count_100":13,"count_300":299,"count_50":0,"count_geki":null,"count_katu":null,"count_miss":0},"user_id":30832844,"score_id":4701471226,"rank":"S","pp":91.8082},"96.3":{"maxcombo":295,"statistics":{"count_100":10,"count_300":297,"count_50":1,"count_geki":null,"count_katu":null,"count_miss":4},"user_id":33437761,"score_id":4697473719,"rank":"A","pp":51.7169},"96.2":{"maxcombo":476,"statistics":{"count_100":14,"count_300":295,"count_50":3,"count_geki":null,"count_katu":null,"count_miss":0},"user_id":27811186,"score_id":4693519122,"rank":"S","pp":83.6686},"94.9":{"maxcombo":475,"statistics":{"count_100":20,"count_300":289,"count_50":3,"count_geki":null,"count_katu":null,"count_miss":0},"user_id":32067119,"score_id":4697863753,"rank":"S","pp":77.8894},"95.2":{"maxcombo":479,"statistics":{"count_100":22,"count_300":290,"count_50":0,"count_geki":null,"count_katu":null,"count_miss":0},"user_id":28444697,"score_id":4694353337,"rank":"S","pp":80.5609},"90.1":{"maxcombo":269,"statistics":{"count_100":38,"count_300":268,"count_50":4,"count_geki":null,"count_katu":null,"count_miss":2},"user_id":20363602,"score_id":4693387539,"rank":"B","pp":39.1683},"91.7":{"maxcombo":285,"statistics":{"count_100":24,"count_300":277,"count_50":8,"count_geki":null,"count_katu":null,"count_miss":3},"user_id":36560346,"score_id":4693934009,"rank":"B","pp":40.9031},"95.1":{"maxcombo":355,"statistics":{"count_100":20,"count_300":290,"count_50":1,"count_geki":null,"count_katu":null,"count_miss":1},"user_id":31508390,"score_id":4701687246,"rank":"A","pp":60.2781},"88.9":{"maxcombo":288,"statistics":{"count_100":43,"count_300":263,"count_50":2,"count_geki":null,"count_katu":null,"count_miss":4},"user_id":18125293,"score_id":4703352554,"rank":"B","pp":36.6008},"91.1":{"maxcombo":355,"statistics":{"count_100":34,"count_300":273,"count_50":0,"count_geki":null,"count_katu":null,"count_miss":5},"user_id":21722830,"score_id":4700448364,"rank":"B","pp":43.2342},"88.1":{"maxcombo":339,"statistics":{"count_100":39,"count_300":261,"count_50":6,"count_geki":null,"count_katu":null,"count_miss":6},"user_id":19449329,"score_id":3657800022,"rank":"B","pp":36.0706}}